innoconv/__init__.py
innoconv/__main__.py
innoconv/cli.py
innoconv/constants.py
innoconv/manifest.py
innoconv/metadata.py
innoconv/runner.py
innoconv/traverse_ast.py
innoconv/utils.py
innoconv/ext/__init__.py
innoconv/ext/abstract.py
innoconv/ext/copy_static.py
innoconv/ext/generate_toc.py
innoconv/ext/index_terms.py
innoconv/ext/join_strings.py
innoconv/ext/number_boxes.py
innoconv/ext/tikz2svg.py
innoconv/ext/write_manifest.py
innoconv-0.1.3.dist-info/LICENSE.txt
innoconv-0.1.3.dist-info/METADATA
innoconv-0.1.3.dist-info/WHEEL
innoconv-0.1.3.dist-info/entry_points.txt
innoconv-0.1.3.dist-info/top_level.txt
innoconv-0.1.3.dist-info/RECORD
