Metadata-Version: 2.1
Name: innoconv
Version: 0.1.3
Summary: Converter for interactive educational content.
Home-page: https://gitlab.tu-berlin.de/innodoc/innoconv
Author: Mirko Dietrich
Author-email: dietrich@math.tu-berlin.de
License: GPLv3
Project-URL: Documentation, https://readthedocs.org/projects/innoconv/
Keywords: innodoc,pandoc,markdown,education
Platform: UNKNOWN
Classifier: Development Status :: 4 - Beta
Classifier: Environment :: Console
Classifier: Intended Audience :: Education
Classifier: Intended Audience :: End Users/Desktop
Classifier: Intended Audience :: Science/Research
Classifier: License :: OSI Approved :: GNU General Public License v3 or later (GPLv3+)
Classifier: Operating System :: POSIX :: Linux
Classifier: Programming Language :: Python
Classifier: Programming Language :: Python :: 3
Classifier: Programming Language :: Python :: 3 :: Only
Classifier: Programming Language :: Python :: 3.6
Classifier: Programming Language :: Python :: 3.7
Classifier: Programming Language :: Python :: 3.8
Classifier: Programming Language :: Python :: 3.9
Classifier: Topic :: Education
Classifier: Topic :: Text Processing :: Markup
Classifier: Topic :: Scientific/Engineering
Requires-Python: >=3.6.0
Requires-Dist: click (<8,>=7)
Requires-Dist: coloredlogs (<15,>=14)
Requires-Dist: python-slugify (<5,>=4)
Requires-Dist: PyYAML (<6,>=5)
